dual_port_ram.v
`timescale 1ns / 1ps

module dual_port_ram #(
    parameter ADDR_WIDTH = 8,
    parameter DATA_WIDTH = 8,
    parameter DEPTH      = 256
)(
    input clk_a,
    input clk_b,

    input write_enable_a,
    input write_enable_b,

    input output_enable_a,
    input output_enable_b,

    input  [ADDR_WIDTH-1:0] address_a,
    input  [ADDR_WIDTH-1:0] address_b,

    input  [DATA_WIDTH-1:0] data_in_a,
    input  [DATA_WIDTH-1:0] data_in_b,

    output reg [DATA_WIDTH-1:0] data_out_a,
    output reg [DATA_WIDTH-1:0] data_out_b,

    output wire collision
);

    // Proper 2D memory declaration
    reg [DATA_WIDTH-1:0] memory [0:DEPTH-1];

    // Combinational collision detection
    assign collision = write_enable_a & write_enable_b &
                       (address_a == address_b);

    // Port A — clk_a domain
    always @(posedge clk_a) begin
        if (write_enable_a)
            memory[address_a] <= data_in_a;

        if (output_enable_a)
            data_out_a <= memory[address_a];
        else
            data_out_a <= {DATA_WIDTH{1'b0}};
    end

    // Port B — clk_b domain
    // Port A wins on collision; Port B write is suppressed
    always @(posedge clk_b) begin
        if (write_enable_b && !collision)
            memory[address_b] <= data_in_b;

        if (output_enable_b)
            data_out_b <= memory[address_b];
        else
            data_out_b <= {DATA_WIDTH{1'b0}};
    end

endmodule

tb_dual_port_ram.v
`timescale 1ns / 1ps

module tb_dual_port_ram;

    reg        clk_a = 0, clk_b = 0;
    reg        write_enable_a = 0, write_enable_b = 0;
    reg        output_enable_a = 0, output_enable_b = 0;
    reg  [7:0] address_a = 0, address_b = 0;
    reg  [7:0] data_in_a = 0, data_in_b = 0;
    wire [7:0] data_out_a, data_out_b;
    wire       collision;

    dual_port_ram #(
        .ADDR_WIDTH(8),
        .DATA_WIDTH(8),
        .DEPTH(256)
    ) uut (
        .clk_a          (clk_a),
        .clk_b          (clk_b),
        .write_enable_a (write_enable_a),
        .write_enable_b (write_enable_b),
        .output_enable_a(output_enable_a),
        .output_enable_b(output_enable_b),
        .address_a      (address_a),
        .address_b      (address_b),
        .data_in_a      (data_in_a),
        .data_in_b      (data_in_b),
        .data_out_a     (data_out_a),
        .data_out_b     (data_out_b),
        .collision      (collision)
    );

    // Fixed: use <= for clock toggles to suppress BLKSEQ warning
    always #5  clk_a <= ~clk_a;
    always #7  clk_b <= ~clk_b;

    // ----------------------------------------------------------------
    // Scoreboard
    // ----------------------------------------------------------------
    integer pass_count = 0;
    integer fail_count = 0;

    task check;
        input [7:0] expected;
        input [7:0] actual;
        input [7:0] addr;
        input       port;
        begin
            if (actual === expected) begin
                $display("  PASS | Port %s | addr=%0d | got=0x%02h",
                         port ? "B" : "A", addr, actual);
                pass_count = pass_count + 1;
            end else begin
                $display("  FAIL | Port %s | addr=%0d | expected=0x%02h got=0x%02h",
                         port ? "B" : "A", addr, expected, actual);
                fail_count = fail_count + 1;
            end
        end
    endtask

    // ----------------------------------------------------------------
    // Tasks
    // ----------------------------------------------------------------
    task write_a(input [7:0] addr, input [7:0] data);
        begin
            address_a      = addr;
            data_in_a      = data;
            write_enable_a = 1;
            #10;
            write_enable_a = 0;
            #10;
        end
    endtask

    task write_b(input [7:0] addr, input [7:0] data);
        begin
            address_b      = addr;
            data_in_b      = data;
            write_enable_b = 1;
            #14;
            write_enable_b = 0;
            #14;
        end
    endtask

    task read_a(input [7:0] addr, input [7:0] expected);
        begin
            address_a       = addr;
            output_enable_a = 1;
            #10;
            check(expected, data_out_a, addr, 0);
            output_enable_a = 0;
            #10;
        end
    endtask

    task read_b(input [7:0] addr, input [7:0] expected);
        begin
            address_b       = addr;
            output_enable_b = 1;
            #14;
            check(expected, data_out_b, addr, 1);
            output_enable_b = 0;
            #14;
        end
    endtask

    // ----------------------------------------------------------------
    // Stimulus
    // ----------------------------------------------------------------
    initial begin
        $dumpfile("dual_port_ram.vcd");
        $dumpvars(0, tb_dual_port_ram);

        $display("\n========================================");
        $display("  Dual-Port RAM Testbench");
        $display("========================================\n");

        // TEST 1: Basic Port A write/read
        $display("--- TEST 1: Port A write/read ---");
        write_a(8'd0,  8'hAA);
        write_a(8'd1,  8'hBB);
        write_a(8'd2,  8'hCC);
        write_a(8'd3,  8'hDD);
        read_a(8'd0,   8'hAA);
        read_a(8'd1,   8'hBB);
        read_a(8'd2,   8'hCC);
        read_a(8'd3,   8'hDD);

        // TEST 2: Basic Port B write/read
        $display("\n--- TEST 2: Port B write/read ---");
        write_b(8'd10, 8'h11);
        write_b(8'd11, 8'h22);
        write_b(8'd12, 8'h33);
        write_b(8'd13, 8'h44);
        read_b(8'd10,  8'h11);
        read_b(8'd11,  8'h22);
        read_b(8'd12,  8'h33);
        read_b(8'd13,  8'h44);

        // TEST 3: Cross-port reads
        $display("\n--- TEST 3: Cross-port reads ---");
        write_a(8'd20, 8'hAB);
        write_b(8'd21, 8'hCD);
        read_b(8'd20,  8'hAB);
        read_a(8'd21,  8'hCD);

        // TEST 4: output_enable = 0 forces data_out to 0
        $display("\n--- TEST 4: OE=0 forces output to 0 ---");
        write_a(8'd30, 8'hFF);
        #20;
        address_a       = 8'd30;
        output_enable_a = 0;
        #10;
        if (data_out_a === 8'h00) begin
            $display("  PASS | Port A OE=0 | data_out_a=0x%02h", data_out_a);
            pass_count = pass_count + 1;
        end else begin
            $display("  FAIL | Port A OE=0 | expected=0x00 got=0x%02h", data_out_a);
            fail_count = fail_count + 1;
        end

        write_b(8'd31, 8'hFF);
        #20;
        address_b       = 8'd31;
        output_enable_b = 0;
        #14;
        if (data_out_b === 8'h00) begin
            $display("  PASS | Port B OE=0 | data_out_b=0x%02h", data_out_b);
            pass_count = pass_count + 1;
        end else begin
            $display("  FAIL | Port B OE=0 | expected=0x00 got=0x%02h", data_out_b);
            fail_count = fail_count + 1;
        end

        // TEST 5: Collision — Port A wins
        $display("\n--- TEST 5: Collision (Port A wins) ---");
        write_b(8'd50, 8'h00);
        #20;
        address_a      = 8'd50; data_in_a = 8'hAA; write_enable_a = 1;
        address_b      = 8'd50; data_in_b = 8'hBB; write_enable_b = 1;
        #5;
        if (collision === 1'b1) begin
            $display("  PASS | collision flag asserted");
            pass_count = pass_count + 1;
        end else begin
            $display("  FAIL | collision flag not asserted");
            fail_count = fail_count + 1;
        end
        #5;
        write_enable_a = 0; write_enable_b = 0;
        #20;
        read_a(8'd50, 8'hAA);

        // TEST 6: No collision — different addresses
        $display("\n--- TEST 6: No collision (different addresses) ---");
        address_a      = 8'd60; data_in_a = 8'h5A; write_enable_a = 1;
        address_b      = 8'd61; data_in_b = 8'h6B; write_enable_b = 1;
        #5;
        if (collision === 1'b0) begin
            $display("  PASS | no spurious collision");
            pass_count = pass_count + 1;
        end else begin
            $display("  FAIL | spurious collision flagged");
            fail_count = fail_count + 1;
        end
        #5;
        write_enable_a = 0; write_enable_b = 0;
        #20;
        read_a(8'd60, 8'h5A);
        read_b(8'd61, 8'h6B);

        // TEST 7: Boundary addresses
        $display("\n--- TEST 7: Boundary addresses ---");
        write_a(8'h00, 8'hDE);
        write_b(8'hFF, 8'hAD);
        read_a(8'h00,  8'hDE);
        read_b(8'hFF,  8'hAD);

        // TEST 8: Overwrite same address
        $display("\n--- TEST 8: Overwrite ---");
        write_a(8'd70, 8'h01);
        write_a(8'd70, 8'h02);
        read_a(8'd70,  8'h02);
        write_b(8'd71, 8'hF0);
        write_b(8'd71, 8'hF1);
        read_b(8'd71,  8'hF1);

        // Summary
        #50;
        $display("\n========================================");
        $display("  Results: %0d PASSED | %0d FAILED",
                 pass_count, fail_count);
        $display("========================================\n");
        if (fail_count == 0)
            $display("  ALL TESTS PASSED\n");
        else
            $display("  SOME TESTS FAILED\n");

        $finish;
    end

endmodule

obj_dir/dual_port_ram.vcd
$version Generated by VerilatedVcd $end
$timescale 1ps $end

 $scope module TOP $end
  $scope module tb_dual_port_ram $end
   $var wire  8 ' address_a [7:0] $end
   $var wire  8 ( address_b [7:0] $end
   $var wire  1 . clk_a $end
   $var wire  1 / clk_b $end
   $var wire  1 + collision $end
   $var wire  8 ) data_in_a [7:0] $end
   $var wire  8 * data_in_b [7:0] $end
   $var wire  8 0 data_out_a [7:0] $end
   $var wire  8 1 data_out_b [7:0] $end
   $var wire 32 - fail_count [31:0] $end
   $var wire  1 % output_enable_a $end
   $var wire  1 & output_enable_b $end
   $var wire 32 , pass_count [31:0] $end
   $var wire  1 # write_enable_a $end
   $var wire  1 $ write_enable_b $end
   $scope module uut $end
    $var wire 32 2 ADDR_WIDTH [31:0] $end
    $var wire 32 2 DATA_WIDTH [31:0] $end
    $var wire 32 3 DEPTH [31:0] $end
    $var wire  8 ' address_a [7:0] $end
    $var wire  8 ( address_b [7:0] $end
    $var wire  1 . clk_a $end
    $var wire  1 / clk_b $end
    $var wire  1 + collision $end
    $var wire  8 ) data_in_a [7:0] $end
    $var wire  8 * data_in_b [7:0] $end
    $var wire  8 0 data_out_a [7:0] $end
    $var wire  8 1 data_out_b [7:0] $end
    $var wire  1 % output_enable_a $end
    $var wire  1 & output_enable_b $end
    $var wire  1 # write_enable_a $end
    $var wire  1 $ write_enable_b $end
   $upscope $end
  $upscope $end
 $upscope $end
$enddefinitions $end


#0
1#
0$
0%
0&
b00000000 '
b00000000 (
b10101010 )
b00000000 *
0+
b00000000000000000000000000000000 ,
b00000000000000000000000000000000 -
0.
0/
b00000000 0
b00000000 1
b00000000000000000000000000001000 2
b00000000000000000000000100000000 3
#5000
1.
#7000
1/
#10000
0#
0.
#14000
0/
#15000
1.
#20000
1#
b00000001 '
b10111011 )
0.
#21000
1/
#25000
1.
#28000
0/
#30000
0#
0.
#35000
1.
1/
#40000
1#
b00000010 '
b11001100 )
0.
#42000
0/
#45000
1.
#49000
1/
#50000
0#
0.
#55000
1.
#56000
0/
#60000
1#
b00000011 '
b11011101 )
0.
#63000
1/
#65000
1.
#70000
0#
0.
0/
#75000
1.
#77000
1/
#80000
1%
b00000000 '
0.
#84000
0/
#85000
1.
b10101010 0
#90000
0%
b00000000000000000000000000000001 ,
0.
#91000
1/
#95000
1.
b00000000 0
#98000
0/
#100000
1%
b00000001 '
0.
#105000
1.
1/
b10111011 0
#110000
0%
b00000000000000000000000000000010 ,
0.
#112000
0/
#115000
1.
b00000000 0
#119000
1/
#120000
1%
b00000010 '
0.
#125000
1.
b11001100 0
#126000
0/
#130000
0%
b00000000000000000000000000000011 ,
0.
#133000
1/
#135000
1.
b00000000 0
#140000
1%
b00000011 '
0.
0/
#145000
1.
b11011101 0
#147000
1/
#150000
0%
b00000000000000000000000000000100 ,
0.
#154000
0/
#155000
1.
b00000000 0
#160000
1$
b00001010 (
b00010001 *
0.
#161000
1/
#165000
1.
#168000
0/
#170000
0.
#174000
0$
#175000
1.
1/
#180000
0.
#182000
0/
#185000
1.
#188000
1$
b00001011 (
b00100010 *
#189000
1/
#190000
0.
#195000
1.
#196000
0/
#200000
0.
#202000
0$
#203000
1/
#205000
1.
#210000
0.
0/
#215000
1.
#216000
1$
b00001100 (
b00110011 *
#217000
1/
#220000
0.
#224000
0/
#225000
1.
#230000
0$
0.
#231000
1/
#235000
1.
#238000
0/
#240000
0.
#244000
1$
b00001101 (
b01000100 *
#245000
1.
1/
#250000
0.
#252000
0/
#255000
1.
#258000
0$
#259000
1/
#260000
0.
#265000
1.
#266000
0/
#270000
0.
#272000
1&
b00001010 (
#273000
1/
b00010001 1
#275000
1.
#280000
0.
0/
#285000
1.
#286000
0&
b00000000000000000000000000000101 ,
#287000
1/
b00000000 1
#290000
0.
#294000
0/
#295000
1.
#300000
1&
b00001011 (
0.
#301000
1/
b00100010 1
#305000
1.
#308000
0/
#310000
0.
#314000
0&
b00000000000000000000000000000110 ,
#315000
1.
1/
b00000000 1
#320000
0.
#322000
0/
#325000
1.
#328000
1&
b00001100 (
#329000
1/
b00110011 1
#330000
0.
#335000
1.
#336000
0/
#340000
0.
#342000
0&
b00000000000000000000000000000111 ,
#343000
1/
b00000000 1
#345000
1.
#350000
0.
0/
#355000
1.
#356000
1&
b00001101 (
#357000
1/
b01000100 1
#360000
0.
#364000
0/
#365000
1.
#370000
0&
b00000000000000000000000000001000 ,
0.
#371000
1/
b00000000 1
#375000
1.
#378000
0/
#380000
0.
#384000
1#
b00010100 '
b10101011 )
#385000
1.
1/
#390000
0.
#392000
0/
#394000
0#
#395000
1.
#399000
1/
#400000
0.
#404000
1$
b00010101 (
b11001101 *
#405000
1.
#406000
0/
#410000
0.
#413000
1/
#415000
1.
#418000
0$
#420000
0.
0/
#425000
1.
#427000
1/
#430000
0.
#432000
1&
b00010100 (
#434000
0/
#435000
1.
#440000
0.
#441000
1/
b10101011 1
#445000
1.
#446000
0&
b00000000000000000000000000001001 ,
#448000
0/
#450000
0.
#455000
1.
1/
b00000000 1
#460000
1%
b00010101 '
0.
#462000
0/
#465000
1.
b11001101 0
#469000
1/
#470000
0%
b00000000000000000000000000001010 ,
0.
#475000
1.
b00000000 0
#476000
0/
#480000
1#
b00011110 '
b11111111 )
0.
#483000
1/
#485000
1.
#490000
0#
0.
0/
#495000
1.
#497000
1/
#500000
0.
#504000
0/
#505000
1.
#510000
0.
#511000
1/
#515000
1.
#518000
0/
#520000
0.
#525000
1.
1/
#530000
1$
b00011111 (
b11111111 *
b00000000000000000000000000001011 ,
0.
#532000
0/
#535000
1.
#539000
1/
#540000
0.
#544000
0$
#545000
1.
#546000
0/
#550000
0.
#553000
1/
#555000
1.
#558000
#560000
0.
0/
#565000
1.
#567000
1/
#570000
0.
#574000
0/
#575000
1.
#578000
#580000
0.
#581000
1/
#585000
1.
#588000
0/
#590000
0.
#592000
1$
b00110010 (
b00000000 *
b00000000000000000000000000001100 ,
#595000
1.
1/
#600000
0.
#602000
0/
#605000
1.
#606000
0$
#609000
1/
#610000
0.
#615000
1.
#616000
0/
#620000
0.
#623000
1/
#625000
1.
#630000
0.
0/
#635000
1.
#637000
1/
#640000
1#
1$
b00110010 '
b10101010 )
b10111011 *
1+
0.
#644000
0/
#645000
b00000000000000000000000000001101 ,
1.
#650000
0#
0$
0+
0.
#651000
1/
#655000
1.
#658000
0/
#660000
0.
#665000
1.
1/
#670000
1%
0.
#672000
0/
#675000
1.
b10101010 0
#679000
1/
#680000
0%
b00000000000000000000000000001110 ,
0.
#685000
1.
b00000000 0
#686000
0/
#690000
1#
1$
b00111100 '
b00111101 (
b01011010 )
b01101011 *
0.
#693000
1/
#695000
b00000000000000000000000000001111 ,
1.
#700000
0#
0$
0.
0/
#705000
1.
#707000
1/
#710000
0.
#714000
0/
#715000
1.
#720000
1%
0.
#721000
1/
#725000
1.
b01011010 0
#728000
0/
#730000
0%
b00000000000000000000000000010000 ,
0.
#735000
1.
1/
b00000000 0
#740000
1&
0.
#742000
0/
#745000
1.
#749000
1/
b01101011 1
#750000
0.
#754000
0&
b00000000000000000000000000010001 ,
#755000
1.
#756000
0/
#760000
0.
#763000
1/
b00000000 1
#765000
1.
#768000
1#
b00000000 '
b11011110 )
#770000
0.
0/
#775000
1.
#777000
1/
#778000
0#
#780000
0.
#784000
0/
#785000
1.
#788000
1$
b11111111 (
b10101101 *
#790000
0.
#791000
1/
#795000
1.
#798000
0/
#800000
0.
#802000
0$
#805000
1.
1/
#810000
0.
#812000
0/
#815000
1.
#816000
1%
#819000
1/
#820000
0.
#825000
1.
b11011110 0
#826000
0%
b00000000000000000000000000010010 ,
0/
#830000
0.
#833000
1/
#835000
1.
b00000000 0
#836000
1&
#840000
0.
0/
#845000
1.
#847000
1/
b10101101 1
#850000
0&
b00000000000000000000000000010011 ,
0.
#854000
0/
#855000
1.
#860000
0.
#861000
1/
b00000000 1
#864000
1#
b01000110 '
b00000001 )
#865000
1.
#868000
0/
#870000
0.
#874000
0#
#875000
1.
1/
#880000
0.
#882000
0/
#884000
1#
b00000010 )
#885000
1.
#889000
1/
#890000
0.
#894000
0#
#895000
1.
#896000
0/
#900000
0.
#903000
1/
#904000
1%
#905000
1.
b00000010 0
#910000
0.
0/
#914000
0%
b00000000000000000000000000010100 ,
#915000
1.
b00000000 0
#917000
1/
#920000
0.
#924000
1$
b01000111 (
b11110000 *
0/
#925000
1.
#930000
0.
#931000
1/
#935000
1.
#938000
0$
0/
#940000
0.
#945000
1.
1/
#950000
0.
#952000
1$
b11110001 *
0/
#955000
1.
#959000
1/
#960000
0.
#965000
1.
#966000
0$
0/
#970000
0.
#973000
1/
#975000
1.
#980000
1&
0.
0/
#985000
1.
#987000
1/
b11110001 1
#990000
0.
#994000
0&
b00000000000000000000000000010101 ,
0/
#995000
1.
#1000000
0.
#1001000
1/
b00000000 1
